nestdict/__init__.py
nestdict/all_keys.py
nestdict/change_value.py
nestdict/check_keys.py
nestdict/find_in_map.py
nestdict/main.py
tests/__init__.py
tests/test_frozen.py
tests/test_nestdict.py
tests/test_validation.py
nestdict-1.0.1.dist-info/LICENSE
nestdict-1.0.1.dist-info/METADATA
nestdict-1.0.1.dist-info/WHEEL
nestdict-1.0.1.dist-info/top_level.txt
nestdict-1.0.1.dist-info/RECORD
