Metadata-Version: 2.1
Name: nestdict
Version: 1.0.1
Summary: Utility/Helper functions build around dictionary data type in Python
Home-page: https://github.com/abhisaini880/nestdict
Author: Abhishek Saini
Author-email: abhisaini880@email.com
License: Apache License 2.0
License-File: LICENSE
